acdc/__init__.py
acdc/dark_correction.py
acdc/predict_dark_level.py
acdc/run_acdc.py
acdc/subtract_dark_level.py
acdc/analysis/__init__.py
acdc/analysis/analyze_correction.py
acdc/analysis/coadd_x1ds.py
acdc/analysis/compare_backgrounds.py
acdc/analysis/compare_x1ds.py
acdc/analysis/hv_vs_modalgain.py
acdc/analysis/niceplot.mplstyle
acdc/data/__init__.py
acdc/data/superdarks/epoch_superdarks/superdark_FUVA_163_epoch0_binned.asdf.gz
acdc/data/superdarks/epoch_superdarks/superdark_FUVA_163_epoch1_binned.asdf.gz
acdc/data/superdarks/epoch_superdarks/superdark_FUVA_163_epoch2_binned.asdf.gz
acdc/data/superdarks/epoch_superdarks/superdark_FUVA_167_epoch0_binned.asdf.gz
acdc/data/superdarks/epoch_superdarks/superdark_FUVA_167_epoch1_binned.asdf.gz
acdc/data/superdarks/epoch_superdarks/superdark_FUVA_167_epoch2_binned.asdf.gz
acdc/data/superdarks/epoch_superdarks/superdark_FUVA_167_epoch3_binned.asdf.gz
acdc/data/superdarks/epoch_superdarks/superdark_FUVA_167_epoch4_binned.asdf.gz
acdc/data/superdarks/epoch_superdarks/superdark_FUVA_167_epoch5_binned.asdf.gz
acdc/data/superdarks/epoch_superdarks/superdark_FUVA_167_epoch6_binned.asdf.gz
acdc/data/superdarks/epoch_superdarks/superdark_FUVA_167_epoch7_binned.asdf.gz
acdc/data/superdarks/epoch_superdarks/superdark_FUVA_167_epoch8_binned.asdf.gz
acdc/data/superdarks/epoch_superdarks/superdark_FUVA_167_epoch9_binned.asdf.gz
acdc/data/superdarks/epoch_superdarks/superdark_FUVA_169_epoch0_binned.asdf.gz
acdc/data/superdarks/epoch_superdarks/superdark_FUVA_169_epoch1_binned.asdf.gz
acdc/data/superdarks/epoch_superdarks/superdark_FUVA_169_epoch2_binned.asdf.gz
acdc/data/superdarks/epoch_superdarks/superdark_FUVA_169_epoch3_binned.asdf.gz
acdc/data/superdarks/epoch_superdarks/superdark_FUVA_169_epoch4_binned.asdf.gz
acdc/data/superdarks/epoch_superdarks/superdark_FUVA_173_epoch0_binned.asdf.gz
acdc/data/superdarks/epoch_superdarks/superdark_FUVA_173_epoch1_binned.asdf.gz
acdc_hst-1.1.dist-info/LICENSE
acdc_hst-1.1.dist-info/METADATA
acdc_hst-1.1.dist-info/WHEEL
acdc_hst-1.1.dist-info/entry_points.txt
acdc_hst-1.1.dist-info/top_level.txt
acdc_hst-1.1.dist-info/RECORD
