Metadata-Version: 2.1
Name: acdc-hst
Version: 1.1
Summary: Software to perform an optimized FUV (Far Ultraviolet) dark correction to HST COS data (Hubble Space Telescope Cosmic Origins Spectrograph).
Author-email: Jo Taylor <jotaylor@stsci.edu>
License: BSD 3-Clause License
Project-URL: Homepage, https://github.com/jotaylor/cos_dark
Project-URL: Documentation, https://github.com/jotaylor/cos_dark
Project-URL: Source, https://github.com/jotaylor/cos_dark
Project-URL: Tracker, https://github.com/jotaylor/cos_dark/issues
Keywords: astronomy,hst,hubble,cos,ultraviolet,uv,dark,instrumentation,calibration
Classifier: Intended Audience :: Science/Research
Classifier: Topic :: Scientific/Engineering :: Astronomy
Classifier: License :: OSI Approved :: BSD License
Classifier: Natural Language :: English
Classifier: Operating System :: POSIX :: Linux
Classifier: Operating System :: MacOS :: MacOS X
Classifier: Programming Language :: Python :: 3
Requires-Python: >=3.9
License-File: LICENSE
Requires-Dist: asdf
Requires-Dist: astropy
Requires-Dist: calcos
Requires-Dist: crds
Requires-Dist: dask
Requires-Dist: shapely
Requires-Dist: matplotlib
Requires-Dist: numpy
Requires-Dist: pandas
Requires-Dist: pymysql
Requires-Dist: pyyaml
Requires-Dist: sqlalchemy
Requires-Dist: ullyses >=4.1.0
Requires-Dist: wget
Provides-Extra: docs
Requires-Dist: sphinx ; extra == 'docs'
Requires-Dist: sphinx-rtd-theme ; extra == 'docs'
Provides-Extra: viz
Requires-Dist: bokeh >=2.1.1 ; extra == 'viz'
Requires-Dist: datashader >=0.13.0 ; extra == 'viz'
Requires-Dist: holoviews >=1.14.4 ; extra == 'viz'
Requires-Dist: panel >=0.11.3 ; extra == 'viz'
